ixc_compressor.py
ixc_django_compressor-0.2.dist-info/DESCRIPTION.rst
ixc_django_compressor-0.2.dist-info/METADATA
ixc_django_compressor-0.2.dist-info/RECORD
ixc_django_compressor-0.2.dist-info/WHEEL
ixc_django_compressor-0.2.dist-info/metadata.json
ixc_django_compressor-0.2.dist-info/top_level.txt
