Metadata-Version: 2.0
Name: ixc-django-compressor
Version: 0.2
Summary: Improvements to django-compressor.
Home-page: https://github.com/ixc/ixc-django-compressor
Author: Interaction Consortium
Author-email: studio@interaction.net.au
License: MIT
Platform: UNKNOWN
